<?xml version="1.0" encoding="UTF-8"?>
<polar-exchange-file version="1.0" xmlns="http://www.mh-aerotools.de/polar-schema" xmlns:xsi="http://www.w3.org/2001/XMLSchema-instance" xsi:schemaLocation="http://www.mh-aerotools.de/polar-schema polar-schema.xsd">
<comment>The 'PolarBrowser' application, a reader and converter is available
in the software section at:
http://www.MH-AeroTools.de/airfoils/</comment>
<configurations>
<name>NACA 0000</name>
<configuration>
<name>airfoil polar</name>
<copyright>Copyright 2001-2020 © Martin Hepperle</copyright>
<polars origin="JavaFoil">
<polar>
 <name>NACA 0000</name>
 <type>constant Reynolds number</type>
 <reynoldsnumber>500000</reynoldsnumber>
 <machnumber>0.3</machnumber>
 <variables>
  <variable>alpha</variable>
  <variable>Cl</variable>
  <variable>Cd</variable>
  <variable>Cm</variable>
  <variable>xtu</variable>
  <variable>xtl</variable>
  <variable>xsu</variable>
  <variable>xsl</variable>
  <variable>L/D</variable>
  <variable>A.C.</variable>
  <variable>C.P.</variable>
 </variables>
 <datapoints>
  <datapoint>
   <value>-10.0</value>
   <value>-0.094</value>
   <value>0.06639</value>
   <value>0.003</value>
   <value>0.035</value>
   <value>0.035</value>
   <value>0.987</value>
   <value>0.016</value>
   <value>-1.421</value>
   <value>0.290</value>
   <value>0.284</value>
  </datapoint>
  <datapoint>
   <value>-9.0</value>
   <value>-0.085</value>
   <value>0.05802</value>
   <value>0.003</value>
   <value>0.024</value>
   <value>0.024</value>
   <value>0.987</value>
   <value>0.017</value>
   <value>-1.473</value>
   <value>0.291</value>
   <value>0.284</value>
  </datapoint>
  <datapoint>
   <value>-8.0</value>
   <value>-0.076</value>
   <value>0.05088</value>
   <value>0.003</value>
   <value>0.024</value>
   <value>0.024</value>
   <value>0.988</value>
   <value>0.018</value>
   <value>-1.502</value>
   <value>0.290</value>
   <value>0.283</value>
  </datapoint>
  <datapoint>
   <value>-7.0</value>
   <value>-0.067</value>
   <value>0.04472</value>
   <value>0.002</value>
   <value>0.016</value>
   <value>0.016</value>
   <value>0.989</value>
   <value>0.019</value>
   <value>-1.504</value>
   <value>0.309</value>
   <value>0.282</value>
  </datapoint>
  <datapoint>
   <value>-6.0</value>
   <value>-0.058</value>
   <value>0.04402</value>
   <value>0.001</value>
   <value>0.010</value>
   <value>0.003</value>
   <value>0.990</value>
   <value>0.006</value>
   <value>-1.311</value>
   <value>0.308</value>
   <value>0.275</value>
  </datapoint>
  <datapoint>
   <value>-5.0</value>
   <value>-0.048</value>
   <value>0.03899</value>
   <value>0.001</value>
   <value>0.010</value>
   <value>0.003</value>
   <value>0.991</value>
   <value>0.005</value>
   <value>-1.237</value>
   <value>0.284</value>
   <value>0.272</value>
  </datapoint>
  <datapoint>
   <value>-4.0</value>
   <value>-0.039</value>
   <value>0.03515</value>
   <value>0.001</value>
   <value>0.010</value>
   <value>0.002</value>
   <value>0.992</value>
   <value>0.005</value>
   <value>-1.099</value>
   <value>0.281</value>
   <value>0.270</value>
  </datapoint>
  <datapoint>
   <value>-3.0</value>
   <value>-0.029</value>
   <value>0.03546</value>
   <value>0.000</value>
   <value>0.010</value>
   <value>0.002</value>
   <value>0.992</value>
   <value>0.004</value>
   <value>-0.815</value>
   <value>0.230</value>
   <value>0.266</value>
  </datapoint>
  <datapoint>
   <value>-2.0</value>
   <value>-0.067</value>
   <value>0.03065</value>
   <value>0.000</value>
   <value>0.010</value>
   <value>0.002</value>
   <value>0.993</value>
   <value>0.004</value>
   <value>-2.175</value>
   <value>0.240</value>
   <value>0.253</value>
  </datapoint>
  <datapoint>
   <value>-1.0</value>
   <value>-0.077</value>
   <value>0.02944</value>
   <value>-0.000</value>
   <value>0.010</value>
   <value>0.002</value>
   <value>0.994</value>
   <value>0.002</value>
   <value>-2.623</value>
   <value>0.264</value>
   <value>0.250</value>
  </datapoint>
  <datapoint>
   <value>-0.0</value>
   <value>0.010</value>
   <value>0.00838</value>
   <value>-0.001</value>
   <value>0.010</value>
   <value>0.010</value>
   <value>0.995</value>
   <value>0.995</value>
   <value>1.240</value>
   <value>0.258</value>
   <value>0.334</value>
  </datapoint>
  <datapoint>
   <value>1.0</value>
   <value>0.122</value>
   <value>0.00980</value>
   <value>-0.002</value>
   <value>0.003</value>
   <value>0.010</value>
   <value>0.996</value>
   <value>0.997</value>
   <value>12.398</value>
   <value>0.249</value>
   <value>0.263</value>
  </datapoint>
  <datapoint>
   <value>2.0</value>
   <value>0.144</value>
   <value>0.03111</value>
   <value>-0.001</value>
   <value>0.002</value>
   <value>0.010</value>
   <value>0.003</value>
   <value>0.997</value>
   <value>4.639</value>
   <value>0.257</value>
   <value>0.255</value>
  </datapoint>
  <datapoint>
   <value>3.0</value>
   <value>0.032</value>
   <value>0.03531</value>
   <value>-0.001</value>
   <value>0.002</value>
   <value>0.010</value>
   <value>0.003</value>
   <value>0.998</value>
   <value>0.895</value>
   <value>0.245</value>
   <value>0.280</value>
  </datapoint>
  <datapoint>
   <value>4.0</value>
   <value>0.042</value>
   <value>0.03654</value>
   <value>-0.001</value>
   <value>0.002</value>
   <value>0.010</value>
   <value>0.004</value>
   <value>1.000</value>
   <value>1.149</value>
   <value>0.278</value>
   <value>0.280</value>
  </datapoint>
  <datapoint>
   <value>5.0</value>
   <value>0.052</value>
   <value>0.03940</value>
   <value>-0.002</value>
   <value>0.002</value>
   <value>0.010</value>
   <value>0.005</value>
   <value>1.000</value>
   <value>1.331</value>
   <value>0.276</value>
   <value>0.279</value>
  </datapoint>
  <datapoint>
   <value>6.0</value>
   <value>0.063</value>
   <value>0.04478</value>
   <value>-0.002</value>
   <value>0.003</value>
   <value>0.010</value>
   <value>0.006</value>
   <value>1.000</value>
   <value>1.405</value>
   <value>0.303</value>
   <value>0.278</value>
  </datapoint>
  <datapoint>
   <value>7.0</value>
   <value>0.074</value>
   <value>0.04525</value>
   <value>-0.003</value>
   <value>0.016</value>
   <value>0.016</value>
   <value>0.025</value>
   <value>1.000</value>
   <value>1.630</value>
   <value>0.300</value>
   <value>0.286</value>
  </datapoint>
  <datapoint>
   <value>8.0</value>
   <value>0.084</value>
   <value>0.05171</value>
   <value>-0.003</value>
   <value>0.016</value>
   <value>0.016</value>
   <value>0.022</value>
   <value>1.000</value>
   <value>1.630</value>
   <value>0.269</value>
   <value>0.284</value>
  </datapoint>
  <datapoint>
   <value>9.0</value>
   <value>0.095</value>
   <value>0.05955</value>
   <value>-0.003</value>
   <value>0.024</value>
   <value>0.024</value>
   <value>0.020</value>
   <value>1.000</value>
   <value>1.592</value>
   <value>0.267</value>
   <value>0.282</value>
  </datapoint>
  <datapoint>
   <value>10.0</value>
   <value>0.105</value>
   <value>0.06882</value>
   <value>-0.003</value>
   <value>0.024</value>
   <value>0.024</value>
   <value>0.019</value>
   <value>1.000</value>
   <value>1.531</value>
   <value>0.266</value>
   <value>0.281</value>
  </datapoint>
 </datapoints>
</polar>
</polars>
</configuration>
</configurations>
</polar-exchange-file>

