<?xml version="1.0" encoding="UTF-8"?>
<polar-exchange-file version="1.0" xmlns="http://www.mh-aerotools.de/polar-schema" xmlns:xsi="http://www.w3.org/2001/XMLSchema-instance" xsi:schemaLocation="http://www.mh-aerotools.de/polar-schema polar-schema.xsd">
<comment>The 'PolarBrowser' application, a reader and converter is available
in the software section at:
http://www.MH-AeroTools.de/airfoils/</comment>
<configurations>
<name>NACA 0000</name>
<configuration>
<name>airfoil polar</name>
<copyright>Copyright 2001-2020 © Martin Hepperle</copyright>
<polars origin="JavaFoil">
<polar>
 <name>NACA 0000</name>
 <type>constant Reynolds number</type>
 <reynoldsnumber>300000</reynoldsnumber>
 <machnumber>0.2</machnumber>
 <variables>
  <variable>alpha</variable>
  <variable>Cl</variable>
  <variable>Cd</variable>
  <variable>Cm</variable>
  <variable>xtu</variable>
  <variable>xtl</variable>
  <variable>xsu</variable>
  <variable>xsl</variable>
  <variable>L/D</variable>
  <variable>A.C.</variable>
  <variable>C.P.</variable>
 </variables>
 <datapoints>
  <datapoint>
   <value>-10.0</value>
   <value>-0.021</value>
   <value>0.06762</value>
   <value>0.003</value>
   <value>0.035</value>
   <value>0.035</value>
   <value>0.996</value>
   <value>0.018</value>
   <value>-0.310</value>
   <value>0.403</value>
   <value>0.407</value>
  </datapoint>
  <datapoint>
   <value>-9.0</value>
   <value>-0.019</value>
   <value>0.05954</value>
   <value>0.003</value>
   <value>0.024</value>
   <value>0.024</value>
   <value>0.996</value>
   <value>0.018</value>
   <value>-0.319</value>
   <value>0.400</value>
   <value>0.407</value>
  </datapoint>
  <datapoint>
   <value>-8.0</value>
   <value>-0.017</value>
   <value>0.05245</value>
   <value>0.003</value>
   <value>0.016</value>
   <value>0.016</value>
   <value>0.996</value>
   <value>0.019</value>
   <value>-0.323</value>
   <value>0.404</value>
   <value>0.408</value>
  </datapoint>
  <datapoint>
   <value>-7.0</value>
   <value>-0.015</value>
   <value>0.04664</value>
   <value>0.002</value>
   <value>0.016</value>
   <value>0.016</value>
   <value>0.996</value>
   <value>0.019</value>
   <value>-0.320</value>
   <value>0.524</value>
   <value>0.408</value>
  </datapoint>
  <datapoint>
   <value>-6.0</value>
   <value>-0.013</value>
   <value>0.04637</value>
   <value>0.002</value>
   <value>0.010</value>
   <value>0.002</value>
   <value>0.996</value>
   <value>0.005</value>
   <value>-0.276</value>
   <value>0.509</value>
   <value>0.370</value>
  </datapoint>
  <datapoint>
   <value>-5.0</value>
   <value>-0.011</value>
   <value>0.04114</value>
   <value>0.001</value>
   <value>0.010</value>
   <value>0.002</value>
   <value>0.996</value>
   <value>0.004</value>
   <value>-0.260</value>
   <value>0.382</value>
   <value>0.368</value>
  </datapoint>
  <datapoint>
   <value>-4.0</value>
   <value>-0.009</value>
   <value>0.04319</value>
   <value>0.001</value>
   <value>0.010</value>
   <value>0.002</value>
   <value>0.996</value>
   <value>0.004</value>
   <value>-0.198</value>
   <value>0.236</value>
   <value>0.364</value>
  </datapoint>
  <datapoint>
   <value>-3.0</value>
   <value>-0.052</value>
   <value>0.03548</value>
   <value>0.001</value>
   <value>0.010</value>
   <value>0.002</value>
   <value>0.996</value>
   <value>0.003</value>
   <value>-1.454</value>
   <value>0.245</value>
   <value>0.264</value>
  </datapoint>
  <datapoint>
   <value>-2.0</value>
   <value>-0.121</value>
   <value>0.03176</value>
   <value>0.000</value>
   <value>0.010</value>
   <value>0.002</value>
   <value>0.996</value>
   <value>0.003</value>
   <value>-3.821</value>
   <value>0.236</value>
   <value>0.254</value>
  </datapoint>
  <datapoint>
   <value>-1.0</value>
   <value>-0.085</value>
   <value>0.02992</value>
   <value>0.000</value>
   <value>0.010</value>
   <value>0.002</value>
   <value>0.996</value>
   <value>0.003</value>
   <value>-2.857</value>
   <value>0.254</value>
   <value>0.253</value>
  </datapoint>
  <datapoint>
   <value>-0.0</value>
   <value>-0.000</value>
   <value>0.00920</value>
   <value>0.000</value>
   <value>0.010</value>
   <value>0.010</value>
   <value>0.996</value>
   <value>0.996</value>
   <value>-0.000</value>
   <value>0.253</value>
   <value>0.250</value>
  </datapoint>
  <datapoint>
   <value>1.0</value>
   <value>0.085</value>
   <value>0.02992</value>
   <value>-0.000</value>
   <value>0.002</value>
   <value>0.010</value>
   <value>0.003</value>
   <value>0.996</value>
   <value>2.857</value>
   <value>0.254</value>
   <value>0.253</value>
  </datapoint>
  <datapoint>
   <value>2.0</value>
   <value>0.121</value>
   <value>0.03176</value>
   <value>-0.000</value>
   <value>0.002</value>
   <value>0.010</value>
   <value>0.003</value>
   <value>0.996</value>
   <value>3.821</value>
   <value>0.236</value>
   <value>0.254</value>
  </datapoint>
  <datapoint>
   <value>3.0</value>
   <value>0.052</value>
   <value>0.03548</value>
   <value>-0.001</value>
   <value>0.002</value>
   <value>0.010</value>
   <value>0.003</value>
   <value>0.996</value>
   <value>1.454</value>
   <value>0.245</value>
   <value>0.264</value>
  </datapoint>
  <datapoint>
   <value>4.0</value>
   <value>0.009</value>
   <value>0.04319</value>
   <value>-0.001</value>
   <value>0.002</value>
   <value>0.010</value>
   <value>0.004</value>
   <value>0.996</value>
   <value>0.198</value>
   <value>0.236</value>
   <value>0.364</value>
  </datapoint>
  <datapoint>
   <value>5.0</value>
   <value>0.011</value>
   <value>0.04114</value>
   <value>-0.001</value>
   <value>0.002</value>
   <value>0.010</value>
   <value>0.004</value>
   <value>0.996</value>
   <value>0.260</value>
   <value>0.382</value>
   <value>0.368</value>
  </datapoint>
  <datapoint>
   <value>6.0</value>
   <value>0.013</value>
   <value>0.04637</value>
   <value>-0.002</value>
   <value>0.002</value>
   <value>0.010</value>
   <value>0.005</value>
   <value>0.996</value>
   <value>0.276</value>
   <value>0.509</value>
   <value>0.370</value>
  </datapoint>
  <datapoint>
   <value>7.0</value>
   <value>0.015</value>
   <value>0.04664</value>
   <value>-0.002</value>
   <value>0.016</value>
   <value>0.016</value>
   <value>0.019</value>
   <value>0.996</value>
   <value>0.320</value>
   <value>0.524</value>
   <value>0.408</value>
  </datapoint>
  <datapoint>
   <value>8.0</value>
   <value>0.017</value>
   <value>0.05245</value>
   <value>-0.003</value>
   <value>0.016</value>
   <value>0.016</value>
   <value>0.019</value>
   <value>0.996</value>
   <value>0.323</value>
   <value>0.404</value>
   <value>0.408</value>
  </datapoint>
  <datapoint>
   <value>9.0</value>
   <value>0.019</value>
   <value>0.05954</value>
   <value>-0.003</value>
   <value>0.024</value>
   <value>0.024</value>
   <value>0.018</value>
   <value>0.996</value>
   <value>0.319</value>
   <value>0.400</value>
   <value>0.407</value>
  </datapoint>
  <datapoint>
   <value>10.0</value>
   <value>0.021</value>
   <value>0.06762</value>
   <value>-0.003</value>
   <value>0.035</value>
   <value>0.035</value>
   <value>0.018</value>
   <value>0.996</value>
   <value>0.310</value>
   <value>0.403</value>
   <value>0.407</value>
  </datapoint>
 </datapoints>
</polar>
</polars>
</configuration>
</configurations>
</polar-exchange-file>

